borabora-0.1.1.dist-info/licenses/LICENSE
clai/__init__.py
clai/config.py
clai/gemini_client.py
clai/groq_client.py
clai/main.py
borabora-0.1.1.dist-info/METADATA
borabora-0.1.1.dist-info/WHEEL
borabora-0.1.1.dist-info/entry_points.txt
borabora-0.1.1.dist-info/top_level.txt
borabora-0.1.1.dist-info/RECORD
