Metadata-Version: 2.4
Name: borabora
Version: 0.1.1
Summary: Command Line AI Assistant that converts natural language to Unix commands using Groq AI
Home-page: https://github.com/invisible-hand/borabora
Author: AndreyZ
Author-email: AndreyZ <andrey@invisible-hand.dev>
License: MIT
Project-URL: Homepage, https://github.com/invisible-hand/borabora
Project-URL: Repository, https://github.com/invisible-hand/borabora
Project-URL: Issues, https://github.com/invisible-hand/borabora/issues
Keywords: cli,ai,assistant,unix,commands,groq,natural-language
Classifier: Development Status :: 3 - Alpha
Classifier: Intended Audience :: Developers
Classifier: Intended Audience :: System Administrators
Classifier: License :: OSI Approved :: MIT License
Classifier: Operating System :: OS Independent
Classifier: Programming Language :: Python :: 3
Classifier: Programming Language :: Python :: 3.7
Classifier: Programming Language :: Python :: 3.8
Classifier: Programming Language :: Python :: 3.9
Classifier: Programming Language :: Python :: 3.10
Classifier: Programming Language :: Python :: 3.11
Classifier: Topic :: Software Development :: Libraries :: Python Modules
Classifier: Topic :: System :: Systems Administration
Classifier: Topic :: Utilities
Requires-Python: >=3.7
License-File: LICENSE
Requires-Dist: groq>=0.4.0
Dynamic: author
Dynamic: home-page
Dynamic: license-file
Dynamic: requires-python
